README.md
setup.py
quantumtrader_ta/__init__.py
quantumtrader_ta/main.py
quantumtrader_ta.egg-info/PKG-INFO
quantumtrader_ta.egg-info/SOURCES.txt
quantumtrader_ta.egg-info/dependency_links.txt
quantumtrader_ta.egg-info/requires.txt
quantumtrader_ta.egg-info/top_level.txt
quantumtrader_ta/candles/__init__.py
quantumtrader_ta/cycles/__init__.py
quantumtrader_ta/cycles/cs_rsi.py
quantumtrader_ta/momentum/__init__.py
quantumtrader_ta/momentum/vwrsi.py
quantumtrader_ta/overlap/__init__.py
quantumtrader_ta/overlap/alma.py
quantumtrader_ta/overlap/dema.py
quantumtrader_ta/overlap/hma.py
quantumtrader_ta/overlap/rma.py
quantumtrader_ta/overlap/tema.py
quantumtrader_ta/overlap/vwrma.py
quantumtrader_ta/performance/__init__.py
quantumtrader_ta/statistics/__init__.py
quantumtrader_ta/statistics/kde.py
quantumtrader_ta/statistics/wt.py
quantumtrader_ta/trend/__init__.py
quantumtrader_ta/utils/__init__.py
quantumtrader_ta/utils/_candles.py
quantumtrader_ta/utils/_core.py
quantumtrader_ta/utils/_math.py
quantumtrader_ta/utils/_metrics.py
quantumtrader_ta/utils/_signals.py
quantumtrader_ta/utils/_time.py
quantumtrader_ta/utils/_utils.py
quantumtrader_ta/volatility/__init__.py
quantumtrader_ta/volatility/zz.py
quantumtrader_ta/volatility/zz1.py
quantumtrader_ta/volume/__init__.py
quantumtrader_ta/volume/market_profile/__init__.py
quantumtrader_ta/volume/market_profile/utils.py